multiply/__init__.py
multiply/multiplication.py
basic_app-0.1.dist-info/METADATA
basic_app-0.1.dist-info/WHEEL
basic_app-0.1.dist-info/top_level.txt
basic_app-0.1.dist-info/RECORD
