Metadata-Version: 2.1
Name: basic-app
Version: 0.1
Summary: Basic app
Home-page: 
Author: Veena Rao
Author-email: veena.rao@hiro-microdatacenters.nl
License: MIT
